<?xml version="1.0" encoding="utf-8" ?><dwsync><file name="chelsea_newsletter.jpg" server="jaysuthar.com" local="3488722604" remote="11978193392" Dst="-1" /><file name="chelsea_newsletter.pdf" server="jaysuthar.com" local="3488722604" remote="11978193392" Dst="-1" /><file name="hotel.html" server="jaysuthar.com" local="3488722605" remote="11979143792" Dst="-1" /><file name="hotel2.html" server="jaysuthar.com" local="3488722605" remote="11979143792" Dst="-1" /><file name="hotel0.html" server="jaysuthar.com" local="3488722605" remote="11979143792" Dst="-1" /><file name="newsletter.html" server="jaysuthar.com" local="3488722609" remote="11978193392" Dst="-1" /><file name="venue.html" server="jaysuthar.com" local="3488722609" remote="11979230192" Dst="-1" /><file name="chelsea_newsletter.png" server="jaysuthar.com" local="3488722610" remote="11978193392" Dst="-1" /></dwsync>